scatterbrain/__init__.py
scatterbrain/asteroids.py
scatterbrain/background.py
scatterbrain/cupy_numpy_imports.py
scatterbrain/data/sector001/bright_asteroids.hdf
scatterbrain/data/sector002/bright_asteroids.hdf
scatterbrain/data/sector003/bright_asteroids.hdf
scatterbrain/data/sector004/bright_asteroids.hdf
scatterbrain/data/sector005/bright_asteroids.hdf
scatterbrain/data/sector006/bright_asteroids.hdf
scatterbrain/data/sector007/bright_asteroids.hdf
scatterbrain/data/sector008/bright_asteroids.hdf
scatterbrain/data/sector009/bright_asteroids.hdf
scatterbrain/data/sector010/bright_asteroids.hdf
scatterbrain/data/sector011/bright_asteroids.hdf
scatterbrain/data/sector012/bright_asteroids.hdf
scatterbrain/data/sector013/bright_asteroids.hdf
scatterbrain/data/sector014/bright_asteroids.hdf
scatterbrain/data/sector015/bright_asteroids.hdf
scatterbrain/data/sector016/bright_asteroids.hdf
scatterbrain/data/sector017/bright_asteroids.hdf
scatterbrain/data/sector018/bright_asteroids.hdf
scatterbrain/data/sector019/bright_asteroids.hdf
scatterbrain/data/sector020/bright_asteroids.hdf
scatterbrain/data/sector021/bright_asteroids.hdf
scatterbrain/data/sector022/bright_asteroids.hdf
scatterbrain/data/sector023/bright_asteroids.hdf
scatterbrain/data/sector024/bright_asteroids.hdf
scatterbrain/data/sector025/bright_asteroids.hdf
scatterbrain/data/sector026/bright_asteroids.hdf
scatterbrain/data/strap_locs.csv
scatterbrain/data/tess_sector_times.pkl
scatterbrain/designmatrix.py
scatterbrain/scene.py
scatterbrain/tpf.py
scatterbrain/utils.py
scatterbrain/version.py
scatterbrain-0.1.11.dist-info/WHEEL
scatterbrain-0.1.11.dist-info/METADATA
scatterbrain-0.1.11.dist-info/RECORD
