Metadata-Version: 2.1
Name: scatterbrain
Version: 0.1.11
Summary: 
Author: Christina Hedges
Author-email: christina.l.hedges@nasa.gov
Requires-Python: >=3.7.1,<3.10
Classifier: Programming Language :: Python :: 3
Classifier: Programming Language :: Python :: 3.8
Classifier: Programming Language :: Python :: 3.9
Requires-Dist: astropy (>=4.3.1,<5.0.0)
Requires-Dist: fbpca (>=1.0,<2.0)
Requires-Dist: fitsio (>=1.1.5,<2.0.0)
Requires-Dist: matplotlib (>=3.4.3,<4.0.0)
Requires-Dist: multiprocess (>=0.70.12,<0.71.0)
Requires-Dist: numpy (>=1.21.2,<2.0.0)
Requires-Dist: scipy (>=1.7.1,<2.0.0)
Requires-Dist: tess-ephem (>=0.3.0,<0.4.0)
Requires-Dist: tess-locator (>=0.5.0,<0.6.0)
Requires-Dist: tqdm (>=4.62.3,<5.0.0)
